tesla_client/__init__.py
tesla_client/account.py
tesla_client/client.py
tesla_client/fleet_telemetry.py
tesla_client/vehicle.py
tesla_client/vehicle_data_pb2.py
tesla_client-7.1.0.dist-info/LICENSE
tesla_client-7.1.0.dist-info/METADATA
tesla_client-7.1.0.dist-info/WHEEL
tesla_client-7.1.0.dist-info/RECORD
