Metadata-Version: 2.3
Name: tesla-client
Version: 7.1.0
Summary: 
Author: Jimming Cheng
Author-email: jimming@gmail.com
Requires-Python: >=3.9,<4.0
Classifier: Programming Language :: Python :: 3
Classifier: Programming Language :: Python :: 3.9
Classifier: Programming Language :: Python :: 3.10
Classifier: Programming Language :: Python :: 3.11
Classifier: Programming Language :: Python :: 3.12
Classifier: Programming Language :: Python :: 3.13
Requires-Dist: kafka (>=1.3.5,<2.0.0)
Requires-Dist: protobuf (>=6.30.2,<7.0.0)
Requires-Dist: requests (>=2.31.0,<3.0.0)
